mrstock/__init__.py
mrstock/main.py
mrstock-0.0.1.dist-info/LICENSE
mrstock-0.0.1.dist-info/METADATA
mrstock-0.0.1.dist-info/WHEEL
mrstock-0.0.1.dist-info/top_level.txt
mrstock-0.0.1.dist-info/RECORD
