Metadata-Version: 2.1
Name: mrstock
Version: 0.0.1
Summary: Python package for analyzing and predicting stock patterns
Home-page: https://github.com/jahantaila/mrstock
Author: Jahan Taila
Author-email: tailajahan@gmail.com
License: UNKNOWN
Project-URL: Bug Tracker, https://github.com/jahantaila/mrstock/issues
Platform: UNKNOWN
Classifier: Programming Language :: Python :: 3
Classifier: License :: OSI Approved :: MIT License
Classifier: Operating System :: OS Independent
Requires-Python: >=3.6
License-File: LICENSE
